bqscales/__init__.py
bqscales/_frontend.py
bqscales/_version.py
bqscales/scales.py
bqscales/traits.py
bqscales/labextension/package.json
bqscales/labextension/static/305.4901929ce38615c3b698.js
bqscales/labextension/static/404.0007f22d7b3778db677e.js
bqscales/labextension/static/449.23ac0ac7978e26183569.js
bqscales/labextension/static/470.c5bfe269fe424633a2c5.js
bqscales/labextension/static/480.fd1b6c9a85eba0c61686.js
bqscales/labextension/static/737.d209ed9eb42d7b61ab6f.js
bqscales/labextension/static/794.ac95c31703849b5fabc8.js
bqscales/labextension/static/886.7bdaae698bdfe64ba4f4.js
bqscales/labextension/static/911.ec6ba66b89b5d7bc8a5c.js
bqscales/labextension/static/remoteEntry.4245bd0b7fdb8d46aad0.js
bqscales/labextension/static/style.js
bqscales/labextension/static/third-party-licenses.json
bqscales/nbextension/__init__.py
bqscales/nbextension/static/extension.js
bqscales/nbextension/static/index.js
bqscales/nbextension/static/index.js.map
bqscales-0.3.3.data/data/share/jupyter/labextensions/bqscales/package.json
bqscales-0.3.3.data/data/share/jupyter/labextensions/bqscales/static/305.4901929ce38615c3b698.js
bqscales-0.3.3.data/data/share/jupyter/labextensions/bqscales/static/404.0007f22d7b3778db677e.js
bqscales-0.3.3.data/data/share/jupyter/labextensions/bqscales/static/449.23ac0ac7978e26183569.js
bqscales-0.3.3.data/data/share/jupyter/labextensions/bqscales/static/470.c5bfe269fe424633a2c5.js
bqscales-0.3.3.data/data/share/jupyter/labextensions/bqscales/static/480.fd1b6c9a85eba0c61686.js
bqscales-0.3.3.data/data/share/jupyter/labextensions/bqscales/static/737.d209ed9eb42d7b61ab6f.js
bqscales-0.3.3.data/data/share/jupyter/labextensions/bqscales/static/794.ac95c31703849b5fabc8.js
bqscales-0.3.3.data/data/share/jupyter/labextensions/bqscales/static/886.7bdaae698bdfe64ba4f4.js
bqscales-0.3.3.data/data/share/jupyter/labextensions/bqscales/static/911.ec6ba66b89b5d7bc8a5c.js
bqscales-0.3.3.dist-info/METADATA
bqscales-0.3.3.dist-info/WHEEL
bqscales-0.3.3.dist-info/licenses/LICENSE
bqscales-0.3.3.dist-info/RECORD
