Metadata-Version: 2.1
Name: bqscales
Version: 0.3.3
Summary: Grammar of Graphics in Python.
Project-URL: Homepage, https://github.com/bqplot/bqscales
Author: The BQplot Development Team
License: 
License-File: LICENSE
Keywords: bqplot,d3,graphics,ipython,jupyter,plotting,widgets
Requires-Python: >=3.6
Requires-Dist: ipywidgets<9,>=8.0.1
Requires-Dist: numpy>=1.10.4
Requires-Dist: traitlets>=4.3.0
Requires-Dist: traittypes>=0.0.6
